{
  "basic_data": {
    "pathID": "bending-station",
    "name": "Bending Station",
    "additional_name": "",
    "description": "An essential tool in the production of components with bent details, such as enclosures, profiles, or structural elements. The bending station enables precise bending of materials according to specified technical parameters and ensures efficient and repeatable processing.",
    "with_data": false
  },
  "images": [
    "/products/images/bending-station/carousel1.png",
    "/products/images/bending-station/carousel2.png",
    "/products/images/bending-station/carousel3.png",
    "/products/images/bending-station/carousel4.png"
  ],
  "floating_CTA": {
    "title": "Bending Station",
    "image": "/products/images/bending-station/floatingCTA.png",
    "content": "",
    "button": "Request a Quote",
    "form": "/contact",
    "qp": "",
    "ar": ""
  },
  "parameters": [
    {
      "name": "Press",
      "value": "Trumpf"
    },
    {
      "name": "Robot",
      "value": "IRB 4600"
    },
    {
      "name": "Max. Workpiece Size",
      "value": "1500 mm x 1500 mm"
    },
    {
      "name": "Max. Workpiece Thickness",
      "value": "4-5 mm"
    }
  ],
  "main_characteristics": [
    {
      "title": "",
      "content": [
        ""
      ],
      "image": ""
    }
  ],
  "specification": [
    {
      "name": "",
      "param": [
        ""
      ]
    }
  ],
  "additional_products": [
    {
      "name": "TruLaser 3030 fiber | TRUMPF",
      "image": "/products/images/trulaser-3030/carousel1.svg",
      "link": "/product/trulaser-3030"
    },
    {
      "name": "TruLaser Tube 7000 fiber",
      "image": "/products/images/trulaser-7000/carousel1.png",
      "link": "/product/trulaser-7000"
    },
    {
      "name": "5-Axis CNC",
      "image": "/products/images/5-axis-cnc/carousel1.svg",
      "link": "/product/5-axis-cnc"
    },
    {
      "name": "TruPunch 5000 | TRUMPF",
      "image": "/products/images/trupunch-5000/carousel1.png",
      "link": "/product/trupunch-5000"
    },
    {
      "name": "Primus Waterjet INTERMAC",
      "image": "/products/images/waterjet/carousel1.svg",
      "link": "/product/waterjet"
    }
  ]
}
